speech_engine/__init__.py
speech_engine/exceptions.py
speech_engine/tts_google.py
speech_engine/tts_openai.py
speech_engine/tts_witai.py
speech_engine-0.1.1.dist-info/LICENSE
speech_engine-0.1.1.dist-info/METADATA
speech_engine-0.1.1.dist-info/WHEEL
speech_engine-0.1.1.dist-info/top_level.txt
speech_engine-0.1.1.dist-info/RECORD
