Metadata-Version: 2.2
Name: speech_engine
Version: 0.1.1
Summary: Python package for synthesizing text into speech
Home-page: https://github.com/PraaneshSelvaraj/speech_engine
Author: Praanesh
Author-email: praaneshselvaraj2003@gmail.com
Keywords: speech_engine,text2speech,text-to-speech,TTS,speech synthesis,audio generation,natural language processing,language processing,voice synthesis,speech output,speech generation,language synthesis,voice output,audio synthesis,voice generation
Classifier: License :: OSI Approved :: MIT License
Classifier: Intended Audience :: Developers
Classifier: Programming Language :: Python :: 3
License-File: LICENSE
Requires-Dist: gtts
Requires-Dist: playsound
Requires-Dist: openai
Dynamic: author
Dynamic: author-email
Dynamic: classifier
Dynamic: description
Dynamic: description-content-type
Dynamic: home-page
Dynamic: keywords
Dynamic: requires-dist
Dynamic: summary
